{
  "version": "0.6.0",
  "lastUpdated": "2026-04-11T15:30:00Z",
  "sessionId": "jsxgraph-sequencer-001",
  "sources": [
    {
      "id": "src-jxg-api-docs",
      "title": "JSXGraph 1.12.2 API Reference",
      "url": "https://jsxgraph.org/docs/index.html",
      "tier": "tier-1",
      "domain": "ACTION",
      "provenance": "[Official]",
      "summary": "Full API reference for JSXGraph 1.12.2. Confirms element types: CurveIntersection, Derivative, Tracecurve, Intersection, Functiongraph, Glider. JXG.Math.Numerics contains generalizedNewton and chandrupatla root-finding algorithms used internally.",
      "markers": ["jxg-api-v1.12.2"],
      "claims": [
        {
          "id": "claim-001",
          "text": "JSXGraph 1.12.2 has a Derivative element that computes the numerical derivative of any JXG.Curve, including functiongraph. Usage: board.create('derivative', [curve], {dash: 2})",
          "confidence": 0.99,
          "domain": "DATA"
        },
        {
          "id": "claim-002",
          "text": "JSXGraph CurveIntersection creates the REGION intersection of two closed paths (Curve/Polygon/Circle), not individual intersection points. Usage: board.create('curveintersection', [curve1, curve2], {fillColor: 'yellow', fillOpacity: 0.6})",
          "confidence": 0.99,
          "domain": "DATA"
        },
        {
          "id": "claim-003",
          "text": "JSXGraph Tracecurve traces the locus of a point as a Glider sweeps its constraint. Usage: board.create('tracecurve', [glider, tracedPoint]). numberPoints field controls curve resolution. LIMITATION: mover must be a Glider, not a freely dragged functiongraph.",
          "confidence": 0.99,
          "domain": "DATA"
        },
        {
          "id": "claim-004",
          "text": "JXG.Math.Numerics provides: generalizedNewton(c1, c2, t1ini, t2ini), generalizedDampedNewtonCurves(c1, c2, t1ini, t2ini, gamma, eps), root(f, x) as chandrupatla alias, Newton(f, x) for single-variable root-finding. JSXGraph uses these internally for the intersection element.",
          "confidence": 0.99,
          "domain": "LOGIC"
        },
        {
          "id": "claim-005",
          "text": "board.reducedUpdate property: 'If reducedUpdate is set to true then only the dragged element and few (dependent) elements are updated.' Critical for 60fps with 10+ elements.",
          "confidence": 0.99,
          "domain": "ACTION"
        },
        {
          "id": "claim-006",
          "text": "board.minimizeReflow attribute changes the redraw strategy in the SVG rendering engine. Available as board-level configuration for performance tuning.",
          "confidence": 0.95,
          "domain": "ACTION"
        },
        {
          "id": "claim-007",
          "text": "board.isSuspendedRedraw: flag set to true when suspendUpdate() is active, skipping all redraws until unsuspendUpdate() is called.",
          "confidence": 0.99,
          "domain": "ACTION"
        },
        {
          "id": "claim-008",
          "text": "Board modes: BOARD_MODE_DRAG (during drag, objects not highlighted), BOARD_MODE_NONE (normal), BOARD_MODE_MOVE_ORIGIN (panning). board.mouse references the currently dragged object.",
          "confidence": 0.99,
          "domain": "ACTION"
        }
      ]
    },
    {
      "id": "src-jxg-releases",
      "title": "JSXGraph GitHub Releases (v1.9.0-v1.12.2)",
      "url": "https://github.com/jsxgraph/jsxgraph/releases",
      "tier": "tier-1",
      "domain": "ACTION",
      "provenance": "[Official]",
      "summary": "Release notes confirm: v1.12.1 increased precision for intersections of curves with curves or lines (BREAKING CHANGE WARNING). v1.11.0 added CSS class binding to elements enabling SVG filters. v1.9.0 overhauled otherintersection to support forbidden intersection arrays.",
      "markers": ["jxg-releases"],
      "claims": [
        {
          "id": "claim-009",
          "text": "JSXGraph v1.12.1 release: 'Increased precision for intersections (points) of curves with curves or lines.' The intersection algorithm for curves was changed — may affect existing constructions. This confirms the Intersection element supports functiongraph inputs with individual POINTS.",
          "confidence": 0.99,
          "domain": "LOGIC"
        },
        {
          "id": "claim-010",
          "text": "JSXGraph v1.11.0: 'ability to pass the hosting element as a parameter to functions given as values of attributes' — enables context-aware attribute callbacks on any element. Also: CSS classes can now be bound to all JSXGraph elements, enabling SVG filter integration.",
          "confidence": 0.99,
          "domain": "ACTION"
        },
        {
          "id": "claim-011",
          "text": "JSXGraph v1.9.0: otherintersection element overhauled — 'Now it is possible to supply an array of points as forbidden intersection points. This makes it very convenient to visualize situations where more than two intersections arise.' Relevant for multiple functiongraph intersections.",
          "confidence": 0.99,
          "domain": "LOGIC"
        },
        {
          "id": "claim-012",
          "text": "JSXGraph v1.12.2 is identical to v1.12.1, only removing zip files for CDN (jsdelivr) size limits. Functional API is v1.12.1.",
          "confidence": 0.99,
          "domain": "DATA"
        }
      ]
    },
    {
      "id": "src-jxg-board-events",
      "title": "JSXGraph board.on('update') Event Pattern",
      "url": "https://github.com/jsxgraph/jsxgraph/blob/main/examples/hypotrochoid.html",
      "tier": "tier-1",
      "domain": "ACTION",
      "provenance": "[Official]",
      "summary": "Confirmed board.on('update', callback) fires on every board update including drag operations. Can update external HTML elements with coordinate values. Also confirmed element.on('drag/move/up/down') event system from GeometryElement.",
      "markers": ["jxg-events"],
      "claims": [
        {
          "id": "claim-013",
          "text": "board.on('update', function(){ /* read element coords, update labels */ }) fires on every board update. Inside callback, p.X() and p.Y() return current coordinates. Example: board.on('update', function(){ document.getElementById('D').value = g4.X(); })",
          "confidence": 0.99,
          "domain": "ACTION"
        },
        {
          "id": "claim-014",
          "text": "GeometryElement events: 'attribute', 'attribute:key', 'down', 'drag', 'move', 'up', 'over', 'out'. All elements including functiongraph inherit these via JXG.EventEmitter.",
          "confidence": 0.99,
          "domain": "ACTION"
        },
        {
          "id": "claim-015",
          "text": "JXG.addEvent(element.rendNode, 'mouseover', callback, element) works with SVG/VML renderer only. JSXGraph's native .on() system works with Canvas renderer too.",
          "confidence": 0.99,
          "domain": "ACTION"
        }
      ]
    },
    {
      "id": "src-jxg-dynamic-text",
      "title": "JSXGraph Dynamic Text and Draggable Function Patterns",
      "url": "https://jsxgraph.uni-bayreuth.de/wiki/index.php/Draggable_exponential_function",
      "tier": "tier-1",
      "domain": "DATA",
      "provenance": "[Official]",
      "summary": "Dynamic text bound to function coordinates: board.create('text', [xFn, y, contentFn]). Draggable functiongraph defined as function of draggable point's coordinates: auto-updates all dependents via JSXGraph's native dependency system.",
      "markers": ["jxg-dynamic-text", "jxg-drag-pattern"],
      "claims": [
        {
          "id": "claim-016",
          "text": "Dynamic text pattern: board.create('text', [function(){ return p.X() - 0.17; }, 2, function(){ return '$' + Math.floor(p.X() * 10) / 10 + '$'; }]) creates text that auto-updates when point p is dragged.",
          "confidence": 0.99,
          "domain": "DATA"
        },
        {
          "id": "claim-017",
          "text": "Draggable functiongraph via parent point: define functiongraph as function using A.X() and A.Y(), then create text reading same values. When A is dragged, JSXGraph's native dependency chain auto-updates graph + text + all dependents without manual board.update() calls.",
          "confidence": 0.99,
          "domain": "ACTION"
        },
        {
          "id": "claim-018",
          "text": "Opacity as a function pattern: board.create('text', [x, y, msg], { opacity: function(){ return condition ? 1 : 0; }}) enables conditional element visibility triggered by drag state.",
          "confidence": 0.95,
          "domain": "DATA"
        }
      ]
    },
    {
      "id": "src-jxg-suspend-update",
      "title": "JSXGraph suspendUpdate/unsuspendUpdate + Locus Pattern",
      "url": "https://jsxgraph.org/about/releases/",
      "tier": "tier-1",
      "domain": "ACTION",
      "provenance": "[Official]",
      "summary": "board.suspendUpdate() / board.unsuspendUpdate() batch update pattern confirmed in watts_curve tracecurve example. Locus element: board.createElement('locus', [point]) creates geometric locus. Intersection of geometric elements: board.createElement('intersection', [c2,c3,0]) selects index 0 of two intersection points.",
      "markers": ["jxg-batch-update"],
      "claims": [
        {
          "id": "claim-019",
          "text": "batch update pattern: board.suspendUpdate() before creating/mutating multiple elements, board.unsuspendUpdate() after. Prevents N intermediate redraws during construction. Example from watts_curve: suspendUpdate() before 7 element creations, unsuspendUpdate() after.",
          "confidence": 0.99,
          "domain": "ACTION"
        },
        {
          "id": "claim-020",
          "text": "Native intersection of two circles with index selection: board.createElement('intersection', [c2, c3, 0]) returns the first intersection point, board.createElement('intersection', [c2, c3, 1]) returns the second. Index is the third argument.",
          "confidence": 0.99,
          "domain": "LOGIC"
        },
        {
          "id": "claim-021",
          "text": "Locus element: board.createElement('locus', [midpoint], {strokeColor: 'red'}) traces the geometric locus of a point as a glider moves. Different from Tracecurve: locus is computed analytically, tracecurve is sampled numerically.",
          "confidence": 0.95,
          "domain": "DATA"
        }
      ]
    },
    {
      "id": "src-jxg-curve-intersection-wiki",
      "title": "JSXGraph Wiki: Intersection of functiongraphs",
      "url": "https://jsxgraph.uni-bayreuth.de/wiki/index.php/Intersection_of_functiongraphs",
      "tier": "tier-1",
      "domain": "LOGIC",
      "provenance": "[Official]",
      "summary": "Official wiki example shows CurveIntersection (region) for functiongraphs, NOT individual points. To get actual intersection POINTS with coordinates, must use JXG.Math.Numerics.root() with f(x)-g(x)=0, or rely on board.create('intersection', ...) which v1.12.1 improved for curve-curve.",
      "markers": ["jxg-fg-intersection"],
      "claims": [
        {
          "id": "claim-022",
          "text": "CurveIntersection of functiongraphs creates filled intersection REGION, not POINTS. Example: board.create('curveintersection', [curve1, curve2], {fillColor:'yellow', fillOpacity:0.3}). This is useful for teaching |f(x)| fold regions or showing overlap between curves visually.",
          "confidence": 0.99,
          "domain": "LOGIC"
        },
        {
          "id": "claim-023",
          "text": "There is NO official JSXGraph wiki example for intersection POINTS of two functiongraphs. The standard approach is: (1) JXG.Math.Numerics.root(function(x){ return f(x)-g(x); }, initialGuess) to find x, then create a dependent JXG point at (x, f(x)). Or use board.create('intersection', [fg1, fg2, 0]) which v1.12.1 improved.",
          "confidence": 0.90,
          "domain": "LOGIC"
        }
      ]
    },
    {
      "id": "src-jxg-glider",
      "title": "JSXGraph Glider Element with snap and animation",
      "url": "https://github.com/jsxgraph/jsxgraph/blob/main/examples/construct.html",
      "tier": "tier-1",
      "domain": "ACTION",
      "provenance": "[Official]",
      "summary": "Glider is a movable point constrained to a curve/line. Supports: snap-to-grid (snapsizex/snapsizey), snap-to-points (snaptopoints), animation (animateanimated, animatespeed, animatestart/stop/loop/direction), fixed mode. Can serve as drag handle for functiongraph translation.",
      "markers": ["jxg-glider"],
      "claims": [
        {
          "id": "claim-024",
          "text": "Glider elements support snap-to-grid: snapsizex/snapsizey parameters. snaptopoints: true snaps to existing points. These behaviors make gliders suitable as constrained drag handles for teaching demonstrations.",
          "confidence": 0.99,
          "domain": "ACTION"
        },
        {
          "id": "claim-025",
          "text": "Glider infobox: showinfobox: true displays coordinate info. infoboxdigits: 'auto' controls decimal precision. This enables automatic coordinate readout during drag without custom text elements.",
          "confidence": 0.95,
          "domain": "DATA"
        }
      ]
    },
    {
      "id": "src-jxg-numerics",
      "title": "JSXGraph JXG.Math.Numerics API Reference",
      "url": "https://jsxgraph.org/docs/symbols/JXG.Math.Numerics.html",
      "tier": "tier-1",
      "domain": "LOGIC",
      "provenance": "[Official]",
      "summary": "Full numerics API. Root-finding: chandrupatla (via root()), Newton(), fzero(). Curve intersection: generalizedNewton(c1,c2,t1ini,t2ini), generalizedDampedNewtonCurves(c1,c2,t1ini,t2ini,gamma,eps). Integration: GaussLegendre, Romberg, NewtonCotes, Qag. Path simplification: RamerDouglasPeucker.",
      "markers": ["jxg-numerics"],
      "claims": [
        {
          "id": "claim-026",
          "text": "JXG.Math.Numerics.generalizedNewton(c1, c2, t1ini, t2ini): Compute intersection of curves c1 and c2 using generalized Newton-Raphson. t1ini, t2ini are initial parameter guesses. Returns intersection point.",
          "confidence": 0.99,
          "domain": "LOGIC"
        },
        {
          "id": "claim-027",
          "text": "JXG.Math.Numerics.root(f, x, context): abstract method for univariate root finding, alias for chandrupatla. Chandrupatla combines bisection, secant, and inverse quadratic interpolation — more robust than Newton for functions without derivatives. maxIterationsRoot configures max iterations.",
          "confidence": 0.99,
          "domain": "LOGIC"
        },
        {
          "id": "claim-028",
          "text": "For real-time functiongraph intersection during drag: use JXG.Math.Numerics.root(function(x){ return f(x) - g(x); }, lastKnownX) where lastKnownX is the previous intersection x-coordinate as warm start. This enables efficient re-rooting near the previous position.",
          "confidence": 0.85,
          "domain": "LOGIC",
          "note": "[Inference] — derived from API capability, not from an official usage example for this exact pattern"
        }
      ]
    },
    {
      "id": "src-dc5-principles",
      "title": "DevCon 5 Ontology Design Principles and 3-Phase Journey",
      "url": "internal://research/palantir/platform/devcon.md",
      "tier": "tier-1",
      "domain": "LOGIC",
      "provenance": "[Official]",
      "summary": "DevCon 5 (March 2026): Four design principles (DDD/DRY/OCP/PECS). 3-phase product journey: Golden Tables → Operational Decision-Making → AI-First. palantir-math Sequencer is at Phase 2. Key primitives: Interfaces, Structs, Reducers, Derived Properties, Object-Backed Link Types.",
      "markers": ["§DC5-04", "§DC5-05", "§DC5-06"],
      "claims": [
        {
          "id": "claim-029",
          "text": "[§DC5-05] Four ontology design principles: (1) Domain-Driven Design, (2) Don't Repeat Yourself (rule of three), (3) Open for extension, closed for modification, (4) Producer Extends, Consumer Super (PECS). These ARE software design principles applied to ontology.",
          "confidence": 0.99,
          "domain": "LOGIC"
        },
        {
          "id": "claim-030",
          "text": "[§DC5-04] palantir-math Sequencer JSXGraph enhancement is at Phase 2 — Operational Decision-Making: data shapes (JSXGraphScene) exist, now encoding kinetics (real-time intersection logic, drag cascade, dependent element chain) and interactive actions (drag → update → redraw).",
          "confidence": 0.99,
          "domain": "LOGIC"
        },
        {
          "id": "claim-031",
          "text": "[§DC5-03] Real-time decision space encoding: 'fragmented enterprise data must be represented at maximum fidelity.' Applied to canvas: drag position + intersection coordinates + annotation state must be captured at every drag frame for teaching-grade fidelity.",
          "confidence": 0.95,
          "domain": "ACTION"
        },
        {
          "id": "claim-032",
          "text": "[§DC5-06] Key ontology primitives for canvas enhancement: Reducers (collapse multi-value drag history into canonical drag state), Derived Properties (intersection coordinates derived from functiongraph positions), Interfaces (polymorphic drag behavior across Linear/Quadratic/Abs graph families).",
          "confidence": 0.95,
          "domain": "LOGIC"
        }
      ]
    },
    {
      "id": "src-arch-ontology-model",
      "title": "Palantir Ontology Model — SENSE→DECIDE→ACT→LEARN Digital Twin",
      "url": "internal://research/palantir/architecture/ontology-model.md",
      "tier": "tier-1",
      "domain": "LOGIC",
      "provenance": "[Official]",
      "summary": "ARCH-05: Digital Twin = SENSE → DECIDE → ACT → LEARN loop. ARCH-14/15/16: DATA/LOGIC/ACTION domain classification. ARCH-21: Schema = Contract + Instruction + Verification.",
      "markers": ["§ARCH-05", "§ARCH-14", "§ARCH-15", "§ARCH-16"],
      "claims": [
        {
          "id": "claim-033",
          "text": "[§ARCH-05] Digital Twin: SENSE = capture drag event (element position, delta), DECIDE = compute intersection (Newton-Raphson), ACT = update canvas (label coords, ghost curve, derivative), LEARN = record interaction telemetry (drag path, intersection events). All four phases must be covered for complete JSXGraph enhancement.",
          "confidence": 0.95,
          "domain": "LOGIC"
        },
        {
          "id": "claim-034",
          "text": "[§ARCH-15] LOGIC domain = reasoning layer. IntersectionSolver, AbsValueFoldComputer, DependencyGraph, DragSemanticResolver all belong to LOGIC. They derive facts from DATA but do not persist state directly.",
          "confidence": 0.99,
          "domain": "LOGIC"
        },
        {
          "id": "claim-035",
          "text": "[§ARCH-16] ACTION domain = mutations. DragCascadeUpdate, BatchBoardUpdate, AnnotationToggle, TraceCurveRecord are ACTION-domain operations — they change the canvas reality when executed.",
          "confidence": 0.99,
          "domain": "ACTION"
        }
      ]
    },
    {
      "id": "src-jxg-abs-value-fold",
      "title": "Absolute Value Fold Visualization via Ghost Curve Pattern",
      "url": "https://jsxgraph.org/docs/symbols/Functiongraph.html",
      "tier": "tier-2",
      "domain": "LOGIC",
      "provenance": "[Synthesis]",
      "summary": "Synthesized from JSXGraph functiongraph + CurveDifference/CurveIntersection API. |f(x)| fold visualization: create ghost curve as y = -f(x) for x where f(x)<0. Fold line at y=0. Highlight with CurveDifference for region below axis. Dynamic update via translationVector on functiongraph.",
      "markers": ["jxg-abs-fold"],
      "claims": [
        {
          "id": "claim-036",
          "text": "[Synthesis] Absolute value visualization approach: (A) Primary curve f(x), (B) Ghost curve |f(x)| = Math.abs(f(x)), (C) Reflection guide: curve y = -f(x) for negative region (shown dashed), (D) Fold boundary: line at y=0 highlighted between x-intercepts. When f(x) translates vertically (ty parameter), all four update via shared ty closure.",
          "confidence": 0.85,
          "domain": "LOGIC"
        },
        {
          "id": "claim-037",
          "text": "[Synthesis] Real-time absolute value fold during drag: define absGraph = board.create('functiongraph', [function(x){ return Math.abs(f_raw(x) + ty); }]). When ty changes via drag, both f(x)+ty and |f(x)+ty| update simultaneously if both read the same ty variable.",
          "confidence": 0.90,
          "domain": "ACTION"
        }
      ]
    },
    {
      "id": "src-jxg-performance",
      "title": "JSXGraph SVG Performance: minimizeReflow + reducedUpdate",
      "url": "https://jsxgraph.org/docs/symbols/JXG.Board.html",
      "tier": "tier-1",
      "domain": "ACTION",
      "provenance": "[Official]",
      "summary": "Board-level performance controls: reducedUpdate (only update dragged element + direct deps), minimizeReflow (SVG reflow reduction), isSuspendedRedraw (skip all redraws). Critical for 60fps with 10+ interactive elements.",
      "markers": ["jxg-performance"],
      "claims": [
        {
          "id": "claim-038",
          "text": "JSXGraph SVG renderer performance controls: (1) board.reducedUpdate — only recompute dragged element chain, (2) board.suspendUpdate() / board.unsuspendUpdate() — batch mutations, (3) board.minimizeReflow — SVG-specific reflow reduction. All three must be considered for 10+ element 60fps target.",
          "confidence": 0.95,
          "domain": "ACTION"
        },
        {
          "id": "claim-039",
          "text": "[Inference] For real-time drag with 10+ elements: the critical bottleneck is the intersection recomputation on each mouse-move event. Newton-Raphson with warm start (previous intersection x as initial guess) should complete in <1ms for smooth polynomials, well within 16ms frame budget.",
          "confidence": 0.80,
          "domain": "ACTION"
        }
      ]
    },
    {
      "id": "src-jxg-tracecurve-glider-constraint",
      "title": "JSXGraph Trace Curve and Locus Patterns",
      "url": "https://jsxgraph.uni-bayreuth.de/wiki/index.php/Trace_curve",
      "tier": "tier-1",
      "domain": "DATA",
      "provenance": "[Official]",
      "summary": "Tracecurve requires Glider as mover. Not directly applicable to functiongraph drag. Alternative for drag-path recording: use board.on('update') to push current position to a data array, then update a curve.dataX/dataY manually.",
      "markers": ["jxg-trace"],
      "claims": [
        {
          "id": "claim-040",
          "text": "Tracecurve: board.create('tracecurve', [C_glider, S_dependent]) where C_glider is a Glider element and S_dependent is a point whose locus is traced. LIMITATION: C must be a Glider on a constraint. Cannot use for free drag of functiongraphs.",
          "confidence": 0.99,
          "domain": "DATA"
        },
        {
          "id": "claim-041",
          "text": "[Synthesis] For functiongraph drag-path recording: create a curve with empty dataX/dataY, then in board.on('update') or element.on('drag'), push current graph position to dataX/dataY arrays and call curve.update(). This gives a hand-drawn trace effect without JSXGraph-native tracecurve.",
          "confidence": 0.85,
          "domain": "ACTION"
        }
      ]
    },
    {
      "id": "src-orchestration-surfaces",
      "title": "Palantir Builder Surface Principles from Orchestration Map",
      "url": "internal://research/palantir/architecture/orchestration-map.md",
      "tier": "tier-1",
      "domain": "ACTION",
      "provenance": "[Official]",
      "summary": "ORCH-03/ORCH-10: Builder surfaces must be explicit, not implicit. ORCH-10 rule: 'Builder surfaces are explicit, not implicit.' Applies to JSXGraph canvas: teaching annotation overlay, coordinate labels, and interaction affordances must be declared elements, not side effects.",
      "markers": ["§ORCH-03", "§ORCH-10"],
      "claims": [
        {
          "id": "claim-042",
          "text": "[§ORCH-10] Rule: 'Builder surfaces are explicit, not implicit.' Applied to JSXGraph teaching canvas: every annotation element (coordinate label, fold line, derivative display, trace overlay) must be a declared board element with explicit lifecycle, not an ad-hoc DOM mutation.",
          "confidence": 0.90,
          "domain": "ACTION"
        }
      ]
    }
  ],
  "evidence": [
    {
      "id": "ev-001",
      "claim": "claim-009",
      "question_id": "q-jg-02",
      "direction": "supports",
      "quote": "Increased precision for intersections (points) of curves with curves or lines",
      "source": "src-jxg-releases",
      "note": "v1.12.1 improved native Intersection element for curve-curve — palantir-math already at 1.12.2"
    },
    {
      "id": "ev-002",
      "claim": "claim-026",
      "question_id": "q-jg-02",
      "direction": "supports",
      "quote": "generalizedNewton(c1, c2, t1ini, t2ini): Compute an intersection of the curves c1 and c2 with a generalized Newton method",
      "source": "src-jxg-numerics",
      "note": "Available as direct call for custom intersection solver"
    },
    {
      "id": "ev-003",
      "claim": "claim-013",
      "question_id": "q-jg-01",
      "direction": "supports",
      "quote": "board.on('update', function(){ document.getElementById('D').value = g4.X(); })",
      "source": "src-jxg-board-events",
      "note": "board.on('update') fires during drag — can trigger intersection recompute"
    },
    {
      "id": "ev-004",
      "claim": "claim-019",
      "question_id": "q-jg-06",
      "direction": "supports",
      "quote": "board.suspendUpdate() before N element creations, board.unsuspendUpdate() after",
      "source": "src-jxg-suspend-update",
      "note": "BatchBoardUpdate pattern for dependent cascade mutation"
    },
    {
      "id": "ev-005",
      "claim": "claim-005",
      "question_id": "q-jg-06",
      "direction": "supports",
      "quote": "reducedUpdate: If reducedUpdate is set to true then only the dragged element and few dependent elements are updated",
      "source": "src-jxg-api-docs",
      "note": "Critical performance flag for drag scenarios"
    },
    {
      "id": "ev-006",
      "claim": "claim-036",
      "question_id": "q-jg-03",
      "direction": "supports",
      "quote": "[Synthesis] Ghost curve |f(x)| via Math.abs wrapper + reflection guide at y=0",
      "source": "src-jxg-abs-value-fold",
      "note": "Absolute value fold teaching pattern"
    },
    {
      "id": "ev-007",
      "claim": "claim-016",
      "question_id": "q-jg-05",
      "direction": "supports",
      "quote": "board.create('text', [function(){ return p.X()-0.17; }, 2, function(){ return '$' + pos + '$'; }])",
      "source": "src-jxg-dynamic-text",
      "note": "Dynamic coordinate labels for teaching annotation"
    },
    {
      "id": "ev-008",
      "claim": "claim-001",
      "question_id": "q-jg-04",
      "direction": "supports",
      "quote": "board.create('derivative', [curve], {dash: 2})",
      "source": "src-jxg-api-docs",
      "note": "Native derivative element — unused in current palantir-math"
    },
    {
      "id": "ev-009",
      "claim": "claim-040",
      "question_id": "q-jg-04",
      "direction": "neutral",
      "quote": "Tracecurve: board.create('tracecurve', [C_glider, S_dependent]). LIMITATION: mover must be a Glider.",
      "source": "src-jxg-tracecurve-glider-constraint",
      "note": "Tracecurve cannot be used directly for functiongraph drag history — needs custom array approach"
    }
  ],
  "researchQuestionStatus": {
    "q-jg-01": {
      "status": "answered",
      "summary": "board.on('update', cb) fires every drag frame. element.on('drag', cb) at element level. board.suspendUpdate()/unsuspendUpdate() for batch. board.reducedUpdate=true for performance. Native dependency chain: functiongraph defined as function(x){...using A.X()/A.Y()...} auto-updates all dependents when A is dragged."
    },
    "q-jg-02": {
      "status": "answered",
      "summary": "Two approaches: (A) JSXGraph native Intersection element: board.create('intersection', [fg1, fg2, 0]) — v1.12.1 improved precision for curve-curve. Auto-updates as functions change IF functiongraphs are defined with JSXGraph-native dependency (via parent point). (B) Custom solver: JXG.Math.Numerics.root(function(x){return f(x)-g(x);}, warmStart) called in board.on('update'). Warm start (previous intersection x) is critical for <1ms performance."
    },
    "q-jg-03": {
      "status": "answered",
      "summary": "Three visual layers: (1) primary f(x)+ty curve, (2) |f(x)+ty| abs curve via Math.abs wrapper sharing ty variable, (3) reflection guide: dashed y=-f(x) for negative fold region, (4) fold boundary: line at y=0 between x-intercepts. All four share ty closure — update together on drag."
    },
    "q-jg-04": {
      "status": "answered",
      "summary": "Unused native elements: Derivative (numerical derivative curve), OtherIntersection (forbidden-point intersection), CurveDifference/CurveUnion (set operations for curve regions), Transform elements, Integral (area under curve). Tracecurve requires Glider mover — not directly applicable."
    },
    "q-jg-05": {
      "status": "answered",
      "summary": "Dynamic text: board.create('text', [xFn, y, contentFn]) — auto-updates on every board.update(). Coordinate labels bound to intersection point: board.create('text', [function(){return intersectPt.X();}, function(){return intersectPt.Y()+0.3;}, function(){return '('+intersectPt.X().toFixed(2)+', '+intersectPt.Y().toFixed(2)+')';}]). Glider infobox (showinfobox:true) for built-in coordinate display."
    },
    "q-jg-06": {
      "status": "answered",
      "summary": "Performance stack: (1) board.reducedUpdate=true during drag, (2) batch mutations with suspendUpdate/unsuspendUpdate, (3) board.minimizeReflow for SVG, (4) Newton warm start for intersection (<1ms for polynomials), (5) throttle board.on('update') to requestAnimationFrame if needed."
    },
    "q-jg-07": {
      "status": "partial",
      "summary": "graphFamily.ts extension: DDD principle suggests new Interface for DragBehavior per graph family (Linear/Quadratic/Cubic/Abs/Piecewise/Parametric). OCP: open for new families without modifying existing drag semantics. Parametric drag needs separate x(t)/y(t) drag model. Piecewise needs segment-aware drag constraint."
    }
  }
}
